{"brands":{},"keywords":{"this closet":[{"cluster_id":"859528","cluster_name":"Kitchen Utensils & Gadgets","term_norm":"this closet","term_display":"this closet","entity_type":"product_phrase","post_key":"https://reddit.com/r/organization/comments/1uibjlq/any_tips_for_organizing_this_closet","post_id":"","url":"https://reddit.com/r/organization/comments/1uibjlq/any_tips_for_organizing_this_closet","title":"Any tips for organizing this closet?","subreddit":"organization","published_at":"2026-06-28 23:01:53+00:00","text_snippet":"Any tips for organizing this closet?.","context_window":"Any tips for organizing this closet?.","mention_count_in_post":1,"sentiment_compound":0.0,"sentiment_label":"neutral","matched_display":"this closet"}],"any tips":[{"cluster_id":"859528","cluster_name":"Kitchen Utensils & Gadgets","term_norm":"any tips","term_display":"any tips","entity_type":"product_phrase","post_key":"https://reddit.com/r/organization/comments/1uibjlq/any_tips_for_organizing_this_closet","post_id":"","url":"https://reddit.com/r/organization/comments/1uibjlq/any_tips_for_organizing_this_closet","title":"Any tips for organizing this closet?","subreddit":"organization","published_at":"2026-06-28 23:01:53+00:00","text_snippet":"Any tips for organizing this closet?.","context_window":"Any tips for organizing this closet?.","mention_count_in_post":1,"sentiment_compound":0.0,"sentiment_label":"neutral","matched_display":"any tips"}]}}